githubinformer/__init__.py
githubinformer/github_informer.py
githubinformer-0.0.4.dist-info/LICENSE
githubinformer-0.0.4.dist-info/METADATA
githubinformer-0.0.4.dist-info/WHEEL
githubinformer-0.0.4.dist-info/top_level.txt
githubinformer-0.0.4.dist-info/RECORD
