Metadata-Version: 2.1
Name: githubinformer
Version: 0.0.4
Summary: 'A library to get data of open users repositories GitHub.'
Home-page: https://github.com/saneksking
Author: A.A Suvorov
Author-email: saneksking@gmail.com
License: BSD 3-Clause License
Project-URL: Documentation, https://github.com/saneksking/githubinformer/blob/master/README.md
Project-URL: Release notes, https://github.com/saneksking/githubinformer/releases
Keywords: saneksking,githubinformer,github info,github data master
Classifier: Development Status :: 5 - Production/Stable
Classifier: Environment :: Console
Classifier: Intended Audience :: End Users/Desktop
Classifier: Intended Audience :: System Administrators
Classifier: License :: OSI Approved :: BSD License
Classifier: Natural Language :: English
Classifier: Operating System :: OS Independent
Classifier: Operating System :: Microsoft :: Windows
Classifier: Operating System :: POSIX :: Linux
Classifier: Programming Language :: Python :: 3 :: Only
Classifier: Topic :: Software Development :: Libraries :: Python Modules
Classifier: Topic :: Utilities
Requires-Python: >=3.6
License-File: LICENSE
